hello_kjmerf/__init__.py
hello_kjmerf/say_hello.py
hello_kjmerf-2.0.9.dist-info/DESCRIPTION.rst
hello_kjmerf-2.0.9.dist-info/METADATA
hello_kjmerf-2.0.9.dist-info/RECORD
hello_kjmerf-2.0.9.dist-info/WHEEL
hello_kjmerf-2.0.9.dist-info/metadata.json
hello_kjmerf-2.0.9.dist-info/top_level.txt
tests/__init__.py
tests/test_say_hello.py
