Metadata-Version: 2.0
Name: hello-kjmerf
Version: 2.0.9
Summary: A package that says hello to kjmerf
Home-page: https://github.com/kjmerf/hello_kjmerf
Author: Kevin Merfeld
Author-email: kevinjmerfeld@gmail.com
License: UNKNOWN
Platform: UNKNOWN
Classifier: Programming Language :: Python :: 3
Classifier: License :: OSI Approved :: MIT License
Classifier: Operating System :: OS Independent
Requires-Python: >=3.6
